{
  "language": "Python",
  "node_id": "R_kgDOJtb2lg",
  "subscribers_count": 28,
  "stargazers_count": 3786,
  "default_branch": "main",
  "pushed_at": "2026-07-03T00:55:50Z",
  "open_issues_count": 43,
  "topics": [],
  "watchers_count": 3786,
  "fork": false,
  "network_count": 559,
  "size": 192242,
  "updated_at": "2026-07-08T21:43:40Z",
  "archived": false,
  "name": "open-instruct",
  "description": "AllenAI's post-training codebase",
  "private": false,
  "id": 651622038,
  "visibility": "public",
  "forks_count": 559,
  "homepage": "https://allenai.github.io/open-instruct/",
  "full_name": "allenai/open-instruct",
  "disabled": false,
  "created_at": "2023-06-09T16:50:38Z",
  "owner_type": "Organization",
  "license_spdx_id": "Apache-2.0",
  "_note": "person-free filtered; response_sha256 (in observations.jsonl) is of the full upstream body"
}