{
  "pushed_at": "2026-06-29T09:33:50Z",
  "homepage": "https://aivideo.hunyuan.tencent.com",
  "private": false,
  "name": "HunyuanVideo",
  "topics": [
    "diffusion-models",
    "diffusion-transformer",
    "video-generation"
  ],
  "archived": false,
  "subscribers_count": 139,
  "forks_count": 1276,
  "network_count": 1276,
  "default_branch": "main",
  "watchers_count": 12341,
  "disabled": false,
  "visibility": "public",
  "created_at": "2024-11-28T08:38:31Z",
  "fork": false,
  "stargazers_count": 12341,
  "updated_at": "2026-07-16T05:05:09Z",
  "full_name": "Tencent-Hunyuan/HunyuanVideo",
  "node_id": "R_kgDONV-LBQ",
  "open_issues_count": 179,
  "language": "Python",
  "id": 895453957,
  "description": "HunyuanVideo: A Systematic Framework For Large Video Generation Model",
  "size": 109274,
  "owner_type": "Organization",
  "license_spdx_id": "NOASSERTION",
  "_note": "person-free filtered; response_sha256 (in observations.jsonl) is of the full upstream body"
}