{
  "description": "Implementation of DiffDock: Diffusion Steps, Twists, and Turns for Molecular Docking",
  "size": 221295,
  "open_issues_count": 132,
  "id": 545595027,
  "network_count": 355,
  "archived": false,
  "default_branch": "main",
  "full_name": "gcorso/DiffDock",
  "stargazers_count": 1542,
  "private": false,
  "language": "Python",
  "forks_count": 355,
  "created_at": "2022-10-04T16:42:00Z",
  "watchers_count": 1542,
  "visibility": "public",
  "disabled": false,
  "updated_at": "2026-07-10T08:11:57Z",
  "homepage": "https://arxiv.org/abs/2210.01776",
  "pushed_at": "2025-05-02T13:59:19Z",
  "node_id": "R_kgDOIIUekw",
  "name": "DiffDock",
  "fork": false,
  "topics": [
    "binding",
    "computational-biology",
    "diffusion-models",
    "docking",
    "equivariance",
    "machine-learning",
    "non-euclidean-geometry",
    "score-based-models"
  ],
  "subscribers_count": 21,
  "owner_type": "User",
  "license_spdx_id": "MIT",
  "_note": "person-free filtered; response_sha256 (in observations.jsonl) is of the full upstream body"
}