{
  "description": "NVIDIA Cosmos is an open platform of world models, datasets, and tools that enables developers to build Physical AI for robots, autonomous vehicles, smart infrastructure, and more.",
  "size": 272774,
  "open_issues_count": 39,
  "id": 910176789,
  "network_count": 760,
  "archived": false,
  "default_branch": "main",
  "full_name": "NVIDIA/cosmos",
  "stargazers_count": 10973,
  "private": false,
  "language": "Jupyter Notebook",
  "forks_count": 760,
  "created_at": "2024-12-30T17:21:14Z",
  "watchers_count": 10973,
  "visibility": "public",
  "disabled": false,
  "updated_at": "2026-07-10T09:20:23Z",
  "homepage": "https://www.nvidia.com/en-us/ai/cosmos/",
  "pushed_at": "2026-07-10T06:37:22Z",
  "node_id": "R_kgDONkAyFQ",
  "name": "cosmos",
  "fork": false,
  "topics": [],
  "subscribers_count": 93,
  "owner_type": "Organization",
  "license_spdx_id": "NOASSERTION",
  "_note": "person-free filtered; response_sha256 (in observations.jsonl) is of the full upstream body"
}