{
  "watchers_count": 3309,
  "fork": false,
  "forks_count": 299,
  "name": "ROLL",
  "homepage": "https://alibaba.github.io/ROLL/",
  "subscribers_count": 15,
  "open_issues_count": 117,
  "visibility": "public",
  "node_id": "R_kgDOOx_J6Q",
  "private": false,
  "default_branch": "main",
  "network_count": 299,
  "pushed_at": "2026-07-19T01:40:23Z",
  "id": 991939049,
  "stargazers_count": 3309,
  "created_at": "2025-05-28T11:27:18Z",
  "full_name": "alibaba/ROLL",
  "updated_at": "2026-07-19T02:57:28Z",
  "description": "An Efficient and User-Friendly Scaling Library for Reinforcement Learning with Large Language Models",
  "archived": false,
  "topics": [
    "agentic",
    "rlhf",
    "rlvr"
  ],
  "size": 118689,
  "language": "Python",
  "disabled": false,
  "owner_type": "Organization",
  "license_spdx_id": "Apache-2.0",
  "_note": "person-free filtered; response_sha256 (in observations.jsonl) is of the full upstream body"
}