{
  "watchers_count": 7620,
  "fork": false,
  "forks_count": 1341,
  "name": "Isaac-GR00T",
  "homepage": "https://developer.nvidia.com/isaac/gr00t",
  "subscribers_count": 75,
  "open_issues_count": 302,
  "visibility": "public",
  "node_id": "R_kgDOOG946w",
  "private": false,
  "default_branch": "main",
  "network_count": 1341,
  "pushed_at": "2026-07-08T16:49:22Z",
  "id": 946829547,
  "stargazers_count": 7620,
  "created_at": "2025-03-11T18:34:24Z",
  "full_name": "NVIDIA/Isaac-GR00T",
  "updated_at": "2026-07-18T18:49:55Z",
  "description": "NVIDIA Isaac GR00T N1.7 -  A Foundation Model for Generalist Robots.",
  "archived": false,
  "topics": [],
  "size": 68532,
  "language": "Python",
  "disabled": false,
  "owner_type": "Organization",
  "license_spdx_id": "Apache-2.0",
  "_note": "person-free filtered; response_sha256 (in observations.jsonl) is of the full upstream body"
}