{
  "subscribers_count": 136,
  "id": 898968194,
  "stargazers_count": 28161,
  "fork": false,
  "name": "smolagents",
  "full_name": "huggingface/smolagents",
  "created_at": "2024-12-05T11:28:04Z",
  "watchers_count": 28161,
  "description": "🤗 smolagents: a barebones library for agents that think in code.",
  "network_count": 2730,
  "archived": false,
  "homepage": "https://huggingface.co/docs/smolagents",
  "open_issues_count": 665,
  "size": 6685,
  "private": false,
  "pushed_at": "2026-06-23T18:34:53Z",
  "updated_at": "2026-07-03T07:11:21Z",
  "visibility": "public",
  "default_branch": "main",
  "topics": [],
  "node_id": "R_kgDONZUqgg",
  "disabled": false,
  "language": "Python",
  "forks_count": 2730,
  "owner_type": "Organization",
  "license_spdx_id": "Apache-2.0",
  "_note": "person-free filtered; response_sha256 (in observations.jsonl) is of the full upstream body"
}